htlogicalgates/__init__.py
htlogicalgates/_utility.py
htlogicalgates/circuit.py
htlogicalgates/connectivity.py
htlogicalgates/htlogicalgates.py
htlogicalgates/stabilizercode.py
htlogicalgates/grb_interface/__init__.py
htlogicalgates/grb_interface/grb_enviroment.py
htlogicalgates/grb_interface/grb_gates.py
htlogicalgates/grb_interface/grb_math_interface.py
htlogicalgates/resources/__init__.py
htlogicalgates/resources/connectivities.json
htlogicalgates/resources/encodings.json
htlogicalgates/resources/resources.py
htlogicalgates/symplectic_rep/__init__.py
htlogicalgates/symplectic_rep/clifford_gate.py
htlogicalgates/symplectic_rep/helper.py
htlogicalgates/symplectic_rep/integer_symplectic.py
htlogicalgates-0.6.2.dist-info/licenses/LICENSE
htlogicalgates-0.6.2.dist-info/METADATA
htlogicalgates-0.6.2.dist-info/WHEEL
htlogicalgates-0.6.2.dist-info/top_level.txt
htlogicalgates-0.6.2.dist-info/RECORD
