Metadata-Version: 2.4
Name: htlogicalgates
Version: 0.6.2
Summary: Find circuit implementations for logical gates of QECCs.
Author: erkue
License: MIT License
Project-URL: Homepage, https://github.com/erkue/htlogicalgates
Project-URL: Bug Tracker, https://github.com/erkue/htlogicalgates/issues
Keywords: quantum information,quantum error correction,quantum circuit,logical gates
Classifier: Programming Language :: Python :: 3
Classifier: License :: OSI Approved :: MIT License
Classifier: Operating System :: OS Independent
Classifier: Topic :: Scientific/Engineering :: Physics
Classifier: Topic :: Scientific/Engineering :: Mathematics
Classifier: Intended Audience :: Science/Research
Requires-Python: >=3.9
License-File: LICENSE
Requires-Dist: gurobipy>=11.0
Requires-Dist: numpy>=1.23
Requires-Dist: qsalto>=0.2
Provides-Extra: tqdm
Requires-Dist: tqdm>=4.0; extra == "tqdm"
Provides-Extra: qiskit
Requires-Dist: qiskit>=1.0; extra == "qiskit"
Dynamic: license-file
